DataProFileExt/DataPro.py
DataProFileExt/__init__.py
DataProFileExt-0.1.4.dist-info/LICENSE
DataProFileExt-0.1.4.dist-info/METADATA
DataProFileExt-0.1.4.dist-info/WHEEL
DataProFileExt-0.1.4.dist-info/top_level.txt
DataProFileExt-0.1.4.dist-info/RECORD
