Metadata-Version: 2.1
Name: DataProFileExt
Version: 0.1.4
Summary: A package for .DataPro file extensions. .DataPro is like json but worse, however its really easy to use.
Home-page: https://github.com/BlueScriptsAndDies/DataPro-File-Extension
Author: Justin Degrechie
Author-email: justin.doodle3845@gmail.com
Classifier: Programming Language :: Python :: 3
Classifier: License :: OSI Approved :: MIT License
Classifier: Operating System :: OS Independent
Requires-Python: >=3.6
License-File: LICENSE
